odoo/addons/cms_status_message_example/README.rst
odoo/addons/cms_status_message_example/__init__.py
odoo/addons/cms_status_message_example/__manifest__.py
odoo/addons/cms_status_message_example/controllers/__init__.py
odoo/addons/cms_status_message_example/controllers/main.py
odoo/addons/cms_status_message_example/i18n/cms_status_message_example.pot
odoo/addons/cms_status_message_example/static/description/icon.png
odoo/addons/cms_status_message_example/templates/test_page.xml
odoo11_addon_cms_status_message_example-11.0.1.0.0.99.dev2.dist-info/DESCRIPTION.rst
odoo11_addon_cms_status_message_example-11.0.1.0.0.99.dev2.dist-info/METADATA
odoo11_addon_cms_status_message_example-11.0.1.0.0.99.dev2.dist-info/RECORD
odoo11_addon_cms_status_message_example-11.0.1.0.0.99.dev2.dist-info/WHEEL
odoo11_addon_cms_status_message_example-11.0.1.0.0.99.dev2.dist-info/metadata.json
odoo11_addon_cms_status_message_example-11.0.1.0.0.99.dev2.dist-info/top_level.txt
